{
    "key": "group_60c8bbec8bb10",
    "title": "Disclaimer Footer",
    "fields": [
        {
            "key": "field_60c8bbf993326",
            "label": "Footer Disclaimer",
            "name": "footer_disclaimer",
            "type": "textarea",
            "instructions": "",
            "required": 0,
            "conditional_logic": 0,
            "wrapper": {
                "width": "",
                "class": "",
                "id": ""
            },
            "default_value": "Behavioral Grooves participates in partner affiliate programs and may be compensated for endorsements - we only endorse products, books, or resources relevant to the field of behavioral science and that we believe could bring value to your work or personal life.<br>\r\nBehavioral Grooves is a participant in the Amazon Services LLC Associates Program, an affiliate advertising program designed to provide a means for sites to earn advertising fees by advertising and linking to amazon.com.",
            "placeholder": "",
            "maxlength": "",
            "rows": "",
            "new_lines": ""
        }
    ],
    "location": [
        [
            {
                "param": "options_page",
                "operator": "==",
                "value": "acf-options"
            }
        ]
    ],
    "menu_order": 0,
    "position": "normal",
    "style": "default",
    "label_placement": "top",
    "instruction_placement": "label",
    "hide_on_screen": "",
    "active": true,
    "description": "",
    "modified": 1623768075
}